{"stats":{"minecraft:picked_up":{"minecraft:stick":13,"minecraft:crafting_table":2,"minecraft:leather":1,"minecraft:wooden_pickaxe":1,"minecraft:porkchop":4,"minecraft:oak_log":49,"minecraft:raw_copper":3,"crittersandcompanions:dragonfly_wing":2,"minecraft:beef":6,"crittersandcompanions:koi_fish":2,"supplementaries:ash":1,"minecraft:oak_sapling":8,"minecraft:oak_planks":1,"minecraft:cobblestone":32},"minecraft:mined":{"minecraft:crafting_table":2,"gravestone:gravestone":1,"minecraft:oak_log":49,"minecraft:stone":32,"minecraft:oak_planks":1,"minecraft:oak_leaves":5},"minecraft:killed":{"minecraft:pig":2,"crittersandcompanions:koi_fish":2,"enemyexpansion:direwolf":1,"crittersandcompanions:dragonfly":2,"minecraft:cow":3},"minecraft:dropped":{"minecraft:wooden_pickaxe":1},"minecraft:broken":{"minecraft:wooden_axe":1},"minecraft:used":{"minecraft:wooden_axe":54,"minecraft:oak_planks":5,"minecraft:wooden_pickaxe":33,"minecraft:stone_axe":11,"minecraft:crafting_table":3,"minecraft:furnace":1,"minecraft:cooked_porkchop":2},"minecraft:crafted":{"minecraft:oak_planks":196,"minecraft:cooked_porkchop":2,"minecraft:crafting_table":1,"minecraft:stick":4,"minecraft:wooden_pickaxe":1,"minecraft:stone_pickaxe":1,"minecraft:wooden_axe":1,"minecraft:furnace":1,"minecraft:stone_axe":1},"minecraft:custom":{"minecraft:time_since_rest":17112,"minecraft:interact_with_furnace":3,"minecraft:sprint_one_cm":36598,"minecraft:damage_taken":335,"minecraft:walk_one_cm":58590,"minecraft:mob_kills":10,"minecraft:drop":1,"minecraft:damage_dealt":830,"minecraft:swim_one_cm":9130,"minecraft:interact_with_crafting_table":3,"minecraft:fly_one_cm":13466,"minecraft:crouch_one_cm":1914,"minecraft:play_time":27471,"minecraft:deaths":1,"minecraft:sneak_time":628,"minecraft:walk_under_water_one_cm":3638,"minecraft:jump":163,"minecraft:time_since_death":17068,"minecraft:leave_game":2,"minecraft:walk_on_water_one_cm":8530,"minecraft:total_world_time":27471,"minecraft:fall_one_cm":3009}},"DataVersion":3465}